{
	"versions": {
		"installation_schema_version": "2.6",
		"metadata_version": "2.6",
		"release_version": "2.6.1-build.156",
		"javascript_migrations_version": "v1"
	},
	"generation_time": "2019-07-21T03:53:27Z",
	"infrastructure_type": "vsphere",
	"director_configuration": {
		"bosh_recreate_on_next_deploy": true,
		"resurrector_enabled": true,
		"blobstore_type": "local",
		"max_threads": null,
		"database_type": "internal",
		"ntp_servers": ["time.vmware.com"],
		"hm_pager_duty_enabled": false,
		"hm_emailer_enabled": false,
		"vm_password_type": "generate"
	},
	"releases": ["pks-telemetry-2.0.0-build.201-ubuntu-xenial-250.25.tgz", "pxc-0.14.0-ubuntu-xenial-250.25.tgz", "bpm-1.0.4-ubuntu-xenial-250.25.tgz", "pks-vrops-0.13.0-ubuntu-xenial-250.25.tgz", "docker-35.1.0-ubuntu-xenial-250.25.tgz", "sink-resources-release-0.1.32-ubuntu-xenial-250.25.tgz", "kubo-0.31.7-ubuntu-xenial-250.25.tgz", "cf-mysql-36.14.0.1-ubuntu-xenial-250.25.tgz", "uaa-71.0-ubuntu-xenial-250.25.tgz", "nsx-cf-cni-release-2.4.1.13515827.tgz", "pks-vrli-0.9.0-ubuntu-xenial-250.25.tgz", "wavefront-proxy-0.14.0-ubuntu-xenial-250.25.tgz", "on-demand-service-broker-0.26.0-ubuntu-xenial-250.25.tgz", "cfcr-etcd-1.10.0-ubuntu-xenial-250.25.tgz", "backup-and-restore-sdk-1.8.0-ubuntu-xenial-250.25.tgz", "syslog-11.4.0-ubuntu-xenial-250.25.tgz", "kubo-service-adapter-1.4.0-build.230-ubuntu-xenial-250.25.tgz", "pks-nsx-t-1.30.0-ubuntu-xenial-250.25.tgz", "pks-api-1.4.0-build.230-ubuntu-xenial-250.25.tgz"],
	"available_stemcells": [{
		"filename": "bosh-stemcell-315.45-vsphere-esxi-ubuntu-xenial-go_agent.tgz",
		"os": "ubuntu-xenial",
		"version": "315.45"
	}],
	"product_templates": ["a88470403b63.yml"],
	"added_products": {
		"deployed": [{
			"name": "p-bosh",
			"version": "2.6.1-build.156",
			"stemcells": [{
				"filename": "bosh-stemcell-315.45-vsphere-esxi-ubuntu-xenial-go_agent.tgz",
				"os": "ubuntu-xenial",
				"version": "315.45"
			}]
		}],
		"staged": [{
			"name": "p-bosh",
			"version": "2.6.1-build.156",
			"stemcells": [{
				"filename": "bosh-stemcell-315.45-vsphere-esxi-ubuntu-xenial-go_agent.tgz",
				"os": "ubuntu-xenial",
				"version": "315.45"
			}]
		}, {
			"name": "pivotal-container-service",
			"version": "1.4.1-build.4",
			"stemcells": []
		}]
	}
}
